reloadly_airtime/airtime/sdk/Internal/FxRateRequest.py
reloadly_airtime/airtime/sdk/client/AirtimeAPI.py
reloadly_airtime/airtime/sdk/dto/Phone.py
reloadly_airtime/airtime/sdk/dto/Request/EmailTopUpRequest.py
reloadly_airtime/airtime/sdk/dto/Request/PhoneTopUpRequest.py
reloadly_airtime/airtime/sdk/dto/Request/TopupRequest.py
reloadly_airtime/airtime/sdk/dto/Request/Topupable.py
reloadly_airtime/airtime/sdk/dto/Request/__init__.py
reloadly_airtime/airtime/sdk/dto/Response/AccountBalanceInfo.py
reloadly_airtime/airtime/sdk/dto/Response/Country.py
reloadly_airtime/airtime/sdk/dto/Response/Discount.py
reloadly_airtime/airtime/sdk/dto/Response/FxRate.py
reloadly_airtime/airtime/sdk/dto/Response/Operator.py
reloadly_airtime/airtime/sdk/dto/Response/OperatorFxRate.py
reloadly_airtime/airtime/sdk/dto/Response/PinDetail.py
reloadly_airtime/airtime/sdk/dto/Response/Promotion.py
reloadly_airtime/airtime/sdk/dto/Response/SimplifiedCountry.py
reloadly_airtime/airtime/sdk/dto/Response/SimplifiedOperator.py
reloadly_airtime/airtime/sdk/dto/Response/TopupTransaction.py
reloadly_airtime/airtime/sdk/dto/Response/TransactionBalanceInfo.py
reloadly_airtime/airtime/sdk/dto/Response/__init__.py
reloadly_airtime/airtime/sdk/enums/DenominationType.py
reloadly_airtime/airtime/sdk/operation/AccountOperations.py
reloadly_airtime/airtime/sdk/operation/BaseAirtimeOperation.py
reloadly_airtime/airtime/sdk/operation/CountryOperations.py
reloadly_airtime/airtime/sdk/operation/DiscountOperations.py
reloadly_airtime/airtime/sdk/operation/OperatorOperations.py
reloadly_airtime/airtime/sdk/operation/PromotionOperations.py
reloadly_airtime/airtime/sdk/operation/ReportOperations.py
reloadly_airtime/airtime/sdk/operation/TopupOperations.py
reloadly_airtime/airtime/sdk/operation/TransactionHistoryOperations.py
reloadly_airtime/airtime/tests/AirtimeAPIMockServer.py
reloadly_airtime/airtime/tests/client/test_AirtimeAPI.py
reloadly_airtime/airtime/tests/operation/test_AccountOperations.py
reloadly_airtime-1.1.2.dist-info/METADATA
reloadly_airtime-1.1.2.dist-info/WHEEL
reloadly_airtime-1.1.2.dist-info/top_level.txt
reloadly_airtime-1.1.2.dist-info/RECORD
