Metadata-Version: 2.1
Name: reloadly-airtime
Version: 1.1.2
Summary: The Official Python library for Reloadly Airtime APIs
Home-page: https://github.com/Reloadly/reloadly-sdk-python/tree/main/airtime
Author: Reloadly Inc.
Author-email: developers@reloadly.com
License: MIT
Platform: UNKNOWN
Classifier: Programming Language :: Python :: 3
Classifier: Programming Language :: Python :: 3.5
Classifier: Programming Language :: Python :: 3.6
Classifier: Programming Language :: Python :: 3.7
Classifier: Programming Language :: Python :: 3.8
Classifier: License :: OSI Approved :: MIT License
Classifier: Operating System :: OS Independent
Requires-Python: >=2.7, !=3.0.*, !=3.1.*, !=3.2.*, !=3.3.*, !=3.4.*
Requires-Dist: requests
Requires-Dist: jwt
Requires-Dist: opentelemetry-launcher
Requires-Dist: certifi
Requires-Dist: reloadly-core
Requires-Dist: reloadly-auth
